Codebase/__init__.py
Codebase/build_project.py
Codebase/register_to_pypi.py
Codebase/reigster_to_test_pypi.py
Codebase/setup_project_env.py
Codebase/Setup/create_publish_yml.py
Codebase/Setup/create_pyproject_toml.py
hl_makepip-0.1.1.dist-info/licenses/LICENSE
hl_makepip-0.1.1.dist-info/METADATA
hl_makepip-0.1.1.dist-info/WHEEL
hl_makepip-0.1.1.dist-info/top_level.txt
hl_makepip-0.1.1.dist-info/RECORD
