Metadata-Version: 2.4
Name: HL-MakePIP
Version: 0.1.1
Summary: Library to setup and export HL project environments to PIP.
Author-email: StevenNaliwajka <ConvexBurrito5@gmail.com>
Requires-Python: >=3.9
License-File: LICENSE
Requires-Dist: build>=1.2.1
Dynamic: license-file
